{"progression-studios-sidebar":{"search-2":{"title":""},"recent-posts-2":{"title":"","number":5},"recent-comments-2":{"title":"","number":5},"archives-2":{"title":"","count":0,"dropdown":0},"categories-2":{"title":"","count":0,"hierarchical":0,"dropdown":0},"meta-2":{"title":""}},"progression-studios-footer-widgets":{"text-2":{"title":"","text":"<a href=\"http:\/\/zaser.progression-studios.com\/demo-news\/\"><img src=\"http:\/\/zaser.progression-studios.com\/demo-news\/wp-content\/uploads\/sites\/10\/2017\/01\/zaser-white.png\" alt=\"logo\" style=\"display:block; margin-bottom:30px; max-width:140px;\"\/><\/a>\r\nWe design and develop themes for customers of all sizes, specializing in creating stylish, modern.\r\n<br \/><br \/>\r\n<a href=\"http:\/\/zaser.progression-studios.com\/demo-news\/\">View the Latest News<\/a>","filter":false},"pyre_progression_studios_widget_media-widget-feat-2":{"title":"Recent Posts","progression_studios_post_count":"3"},"archives-3":{"title":"Archives","count":1,"dropdown":0},"null-instagram-feed-2":{"title":"Instagram","username":"envato","number":"6","size":"large","target":"_blank","link":""}}}